{"_type":"export","__export_format":4,"__export_date":"2024-03-21T15:44:22.793Z","__export_source":"insomnia.desktop.app:v2023.5.8","resources":[{"_id":"req_1bd4efba1e9348dda254291ffdced7c7","parentId":"fld_417c4cb6f7804d6db2cd0b027efdde7e","modified":1711034324916,"created":1711025356534,"url":"{{ _.uri }}/admin/books","name":"Create Book","description":"","method":"POST","body":{"mimeType":"application/json","text":"{\n\t\"Title\": \"lord of the rings\",\n\t\"Author\": \"J R R Tolkien\",\n\t\"Quantity\": 5\n}"},"parameters":[],"headers":[{"name":"Content-Type","value":"application/json"},{"name":"User-Agent","value":"insomnia/2023.5.8"}],"authentication":{},"metaSortKey":-1711026575868,"isPrivate":false,"settingStoreCookies":true,"settingSendCookies":true,"settingDisableRenderRequestBody":false,"settingEncodeUrl":true,"settingRebuildPath":true,"settingFollowRedirects":"global","_type":"request"},{"_id":"fld_417c4cb6f7804d6db2cd0b027efdde7e","parentId":"wrk_0a05f136729247fb9b0246a89f3c22ed","modified":1711026568800,"created":1711026568800,"name":"Admin","description":"","environment":{},"environmentPropertyOrder":null,"metaSortKey":-1711026568800,"_type":"request_group"},{"_id":"wrk_0a05f136729247fb9b0246a89f3c22ed","parentId":null,"modified":1710970343070,"created":1710970343070,"name":"Pego","description":"","scope":"collection","_type":"workspace"},{"_id":"req_56d07e7706534da78363220b98e47569","parentId":"fld_417c4cb6f7804d6db2cd0b027efdde7e","modified":1711034349001,"created":1711026318545,"url":"{{ _.uri }}/admin/books/1","name":"Update Book","description":"","method":"PUT","body":{"mimeType":"application/json","text":"{\n\t\"Quantity\": 1\n}"},"parameters":[],"headers":[{"name":"Content-Type","value":"application/json"},{"name":"User-Agent","value":"insomnia/2023.5.8"}],"authentication":{},"metaSortKey":-1711026575768,"isPrivate":false,"settingStoreCookies":true,"settingSendCookies":true,"settingDisableRenderRequestBody":false,"settingEncodeUrl":true,"settingRebuildPath":true,"settingFollowRedirects":"global","_type":"request"},{"_id":"req_15bef79ddce54fa09e659ef875f74b74","parentId":"fld_417c4cb6f7804d6db2cd0b027efdde7e","modified":1711034502134,"created":1711018699142,"url":"{{ _.uri }}/admin/books/1","name":"Delete Book","description":"","method":"DELETE","body":{},"parameters":[],"headers":[{"name":"User-Agent","value":"insomnia/2023.5.8"}],"authentication":{"type":"bearer","token":"eyJhbGciOiJIUzI1NiIsInR5cCI6IkpXVCJ9.eyJzdWIiOiIxMjM0NTY3ODkwIiwibmFtZSI6IkpvaG4gRG9lIiwiaWF0IjoxNTE2MjM5MDIyLCJjbGFpbXMiOlsiYWRtaW4iXX0.L__qxtxwHIvUREtUqbSalZ9hJzd4C__MOtuOeFph5hU","prefix":"Bearer"},"metaSortKey":-1711026575718,"isPrivate":false,"settingStoreCookies":true,"settingSendCookies":true,"settingDisableRenderRequestBody":false,"settingEncodeUrl":true,"settingRebuildPath":true,"settingFollowRedirects":"global","_type":"request"},{"_id":"req_36c182c49b204fce8f0b46bf567730ed","parentId":"wrk_0a05f136729247fb9b0246a89f3c22ed","modified":1711018363814,"created":1711018319069,"url":"{{ _.uri }}/books","name":"Get Books","description":"","method":"GET","body":{},"parameters":[],"headers":[{"name":"User-Agent","value":"insomnia/2023.5.8"}],"authentication":{},"metaSortKey":-1711018319069,"isPrivate":false,"settingStoreCookies":true,"settingSendCookies":true,"settingDisableRenderRequestBody":false,"settingEncodeUrl":true,"settingRebuildPath":true,"settingFollowRedirects":"global","_type":"request"},{"_id":"req_f71ca440837f42e1aa32af859981659d","parentId":"wrk_0a05f136729247fb9b0246a89f3c22ed","modified":1711025900462,"created":1710970345760,"url":"{{ _.uri }}/book/1","name":"Get Book","description":"","method":"GET","body":{},"parameters":[{"id":"pair_e50e7f9ca5ba458b851eb18bc998989d","name":"id","value":"5","description":""}],"headers":[{"name":"User-Agent","value":"insomnia/2023.5.8"}],"authentication":{"type":"bearer","token":"eyJhbGciOiJIUzI1NiIsInR5cCI6IkpXVCJ9.eyJzdWIiOiIxMjM0NTY3ODkwIiwibmFtZSI6IkpvaG4gRG9lIiwiaWF0IjoxNTE2MjM5MDIyLCJjbGFpbXMiOlsiYWRtaW4iXX0.L__qxtxwHIvUREtUqbSalZ9hJzd4C__MOtuOeFph5hU","prefix":"Bearer","disabled":true},"metaSortKey":-1710970345761,"isPrivate":false,"settingStoreCookies":true,"settingSendCookies":true,"settingDisableRenderRequestBody":false,"settingEncodeUrl":true,"settingRebuildPath":true,"settingFollowRedirects":"global","_type":"request"},{"_id":"env_f8e3fd4ae424ad025c512260fcaa354c09b1d4be","parentId":"wrk_0a05f136729247fb9b0246a89f3c22ed","modified":1711034247998,"created":1710970343075,"name":"Base Environment","data":{"uri":"https://localhost:60890"},"dataPropertyOrder":{"&":["uri"]},"color":null,"isPrivate":false,"metaSortKey":1710970343075,"_type":"environment"},{"_id":"jar_f8e3fd4ae424ad025c512260fcaa354c09b1d4be","parentId":"wrk_0a05f136729247fb9b0246a89f3c22ed","modified":1710970343076,"created":1710970343076,"name":"Default Jar","cookies":[],"_type":"cookie_jar"}]}